hydroeval/__init__.py
hydroeval/hydroeval.py
hydroeval/objective_functions.py
hydroeval/version.py
hydroeval-0.1.0.dist-info/LICENCE.rst
hydroeval-0.1.0.dist-info/METADATA
hydroeval-0.1.0.dist-info/WHEEL
hydroeval-0.1.0.dist-info/top_level.txt
hydroeval-0.1.0.dist-info/RECORD
