Metadata-Version: 2.1
Name: hydroeval
Version: 0.1.0
Summary: HydroEval: An Evaluator for Streamflow Time Series In Python
Home-page: UNKNOWN
Author: Thibault Hallouin
Author-email: thibault.hallouin@ucdconnect.ie
License: GPLv3
Download-URL: https://pypi.python.org/pypi/hydroeval
Project-URL: Bug Tracker, https://github.com/thibhlln/hydroeval/issues
Project-URL: Source Code, https://github.com/thibhlln/hydroeval
Project-URL: Documentation, https://thibhlln.github.io/hydroeval
Platform: UNKNOWN
Classifier: Development Status :: 4 - Beta
Classifier: Natural Language :: English
Classifier: Intended Audience :: Science/Research
Classifier: Intended Audience :: Developers
Classifier: Topic :: Scientific/Engineering :: Hydrology
Classifier: Operating System :: MacOS
Classifier: Operating System :: Microsoft :: Windows
Classifier: Operating System :: POSIX :: Linux
Classifier: License :: OSI Approved :: GNU General Public License v3 (GPLv3)
Classifier: Programming Language :: Python :: 3.7
Classifier: Programming Language :: Python :: 3.8
Classifier: Programming Language :: Python :: 3.9
Classifier: Programming Language :: Python :: Implementation :: CPython
